images_dataset/__init__.py
images_dataset/__init__.pyi
images_dataset/cli.py
images_dataset/compression.py
images_dataset/dataset.py
images_dataset/meta.py
images_dataset-0.1.0.dist-info/METADATA
images_dataset-0.1.0.dist-info/WHEEL
images_dataset-0.1.0.dist-info/entry_points.txt
images_dataset-0.1.0.dist-info/top_level.txt
images_dataset-0.1.0.dist-info/RECORD
