Metadata-Version: 2.1
Name: images-dataset
Version: 0.1.0
Summary: Simple, composable standard for storing image datasets
Author-email: Marcel Claramunt <marcel@moveread.com>
Project-URL: repo, https://github.com/moveread/REPO.git
Requires-Python: >=3.10
Requires-Dist: pydantic
Requires-Dist: haskellian
